<annotation>
	<folder>mallophora</folder>
	<filename>Beelzebub_Bee-Killer_Mallophora_leschenaulti_247.jpg</filename>
	<path>/Users/razin/Desktop/malloph/mallophora/Beelzebub_Bee-Killer_Mallophora_leschenaulti_247.jpg</path>
	<source>
		<database>Unknown</database>
	</source>
	<size>
		<width>768</width>
		<height>1024</height>
		<depth>3</depth>
	</size>
	<segmented>0</segmented>
	<object>
		<name>mallophora</name>
		<pose>Unspecified</pose>
		<truncated>0</truncated>
		<difficult>0</difficult>
		<bndbox>
			<xmin>227</xmin>
			<ymin>273</ymin>
			<xmax>542</xmax>
			<ymax>883</ymax>
		</bndbox>
	</object>
</annotation>
