<annotation>
	<folder>centris</folder>
	<filename>Red-legged_Centris_Centris_rhodopus_147.jpg</filename>
	<path>C:\USF\USF_Bees\data\bee_images\centris\Red-legged_Centris_Centris_rhodopus_147.jpg</path>
	<source>
		<database>Unknown</database>
	</source>
	<size>
		<width>1024</width>
		<height>838</height>
		<depth>3</depth>
	</size>
	<segmented>0</segmented>
	<object>
		<name>centris</name>
		<pose>Unspecified</pose>
		<truncated>0</truncated>
		<difficult>0</difficult>
		<bndbox>
			<xmin>259</xmin>
			<ymin>137</ymin>
			<xmax>673</xmax>
			<ymax>673</ymax>
		</bndbox>
	</object>
</annotation>
