<annotation>
	<folder>rustybee</folder>
	<filename>Rusty-patched_Bumble_Bee_Bombus_affinis_241.jpg</filename>
	<path>C:\USF\USF_Bees\data\bee_images\rustybee\Rusty-patched_Bumble_Bee_Bombus_affinis_241.jpg</path>
	<source>
		<database>Unknown</database>
	</source>
	<size>
		<width>768</width>
		<height>1024</height>
		<depth>3</depth>
	</size>
	<segmented>0</segmented>
	<object>
		<name>rustybee</name>
		<pose>Unspecified</pose>
		<truncated>0</truncated>
		<difficult>0</difficult>
		<bndbox>
			<xmin>188</xmin>
			<ymin>240</ymin>
			<xmax>405</xmax>
			<ymax>439</ymax>
		</bndbox>
	</object>
</annotation>
