<annotation>
	<folder>bumblebee</folder>
	<filename>Common_Eastern_Bumble_Bee_Bombus_impatiens_282.jpg</filename>
	<path>C:\USF\USF_Bees\data\bee_images\bumblebee\Common_Eastern_Bumble_Bee_Bombus_impatiens_282.jpg</path>
	<source>
		<database>Unknown</database>
	</source>
	<size>
		<width>768</width>
		<height>1024</height>
		<depth>3</depth>
	</size>
	<segmented>0</segmented>
	<object>
		<name>bumblebee</name>
		<pose>Unspecified</pose>
		<truncated>0</truncated>
		<difficult>0</difficult>
		<bndbox>
			<xmin>328</xmin>
			<ymin>298</ymin>
			<xmax>629</xmax>
			<ymax>684</ymax>
		</bndbox>
	</object>
</annotation>
