<annotation>
	<folder>unseen_old</folder>
	<filename>Brown-belted_Bumble_Bee_Bombus_griseocollis_6071.jpg</filename>
	<path>/Users/razin/Documents/SCoRe_Lab/bee_data/latest_bumblebee_or_not/unseen_old/Brown-belted_Bumble_Bee_Bombus_griseocollis_6071.jpg</path>
	<source>
		<database>Unknown</database>
	</source>
	<size>
		<width>541</width>
		<height>663</height>
		<depth>3</depth>
	</size>
	<segmented>0</segmented>
	<object>
		<name>bumblebee</name>
		<pose>Unspecified</pose>
		<truncated>0</truncated>
		<difficult>0</difficult>
		<bndbox>
			<xmin>133</xmin>
			<ymin>204</ymin>
			<xmax>377</xmax>
			<ymax>616</ymax>
		</bndbox>
	</object>
</annotation>
