<annotation>
	<folder>unseen_old</folder>
	<filename>Western_Honey_Bee_Apis_mellifera_7925.jpg</filename>
	<path>/Users/razin/Documents/SCoRe_Lab/bee_data/latest_bumblebee_or_not/unseen_old/Western_Honey_Bee_Apis_mellifera_7925.jpg</path>
	<source>
		<database>Unknown</database>
	</source>
	<size>
		<width>765</width>
		<height>1024</height>
		<depth>3</depth>
	</size>
	<segmented>0</segmented>
	<object>
		<name>not_bumblebee</name>
		<pose>Unspecified</pose>
		<truncated>0</truncated>
		<difficult>0</difficult>
		<bndbox>
			<xmin>262</xmin>
			<ymin>396</ymin>
			<xmax>336</xmax>
			<ymax>483</ymax>
		</bndbox>
	</object>
</annotation>
